atoti_spring_boot_admin/__init__.py
atoti_spring_boot_admin/__resources__/plugin.jar
atoti_spring_boot_admin/_plugin.py
atoti_spring_boot_admin/_resources_directory.py
atoti_spring_boot_admin/py.typed
atoti_server_spring_boot_admin-0.9.12.dist-info/WHEEL
atoti_server_spring_boot_admin-0.9.12.dist-info/entry_points.txt
atoti_server_spring_boot_admin-0.9.12.dist-info/METADATA
atoti_server_spring_boot_admin-0.9.12.dist-info/RECORD
